huunq/__init__.py
huunq/connection.py
huunq/cursor.py
huunq/exceptions.py
huunq/globals.py
huunq/typing.py
huunq/utilities.py
huunq-0.0.2.dist-info/LICENSE
huunq-0.0.2.dist-info/METADATA
huunq-0.0.2.dist-info/WHEEL
huunq-0.0.2.dist-info/top_level.txt
huunq-0.0.2.dist-info/RECORD
