Metadata-Version: 2.1
Name: huunq
Version: 0.0.2
Summary: huunq: Experimental DBAPI2 Interface for kdb+ in Python
Home-page: https://github.com/3ok/huunq
Author: Reda Bouaida
Author-email: reda.bouaida@outlook.com
License: MIT
Platform: UNKNOWN
Classifier: License :: OSI Approved :: MIT License
Classifier: Programming Language :: Python :: 3
Classifier: Programming Language :: Python :: 3 :: Only
Classifier: Programming Language :: Python :: Implementation :: CPython
Classifier: Programming Language :: Python :: Implementation :: PyPy
Requires-Python: >=3.8.1
Requires-Dist: pykx >=2.0.0
Requires-Dist: sqlparams >=6.0.0
Requires-Dist: typing-extensions >=4.6.0 ; python_version < "3.10"
